plottery/__init__.py
plottery/astroplots.py
plottery/patches.py
plottery/plotutils.py
plottery/statsplots.py
plottery-0.6.2.dist-info/LICENSE
plottery-0.6.2.dist-info/METADATA
plottery-0.6.2.dist-info/WHEEL
plottery-0.6.2.dist-info/top_level.txt
plottery-0.6.2.dist-info/RECORD
