Metadata-Version: 2.1
Name: plottery
Version: 0.6.2
Summary: Custom plotting tools
Home-page: https://github.com/cristobal-sifon/plottery
Author: Cristobal Sifon
Author-email: cristobal.sifon@pucv.cl
License: UNKNOWN
Platform: UNKNOWN
Classifier: Development Status :: 5 - Production/Stable
Classifier: License :: OSI Approved :: GNU General Public License v3 (GPLv3)
Classifier: Programming Language :: Python
Classifier: Topic :: Scientific/Engineering :: Visualization
